pdfget/__init__.py
pdfget/__main__.py
pdfget/config.py
pdfget/counter.py
pdfget/downloader.py
pdfget/fetcher.py
pdfget/formatter.py
pdfget/logger.py
pdfget/main.py
pdfget/manager.py
pdfget/pmc_oa_service.py
pdfget/pmcid.py
pdfget/searcher.py
pdfget-0.1.2.dist-info/METADATA
pdfget-0.1.2.dist-info/WHEEL
pdfget-0.1.2.dist-info/entry_points.txt
pdfget-0.1.2.dist-info/licenses/LICENSE.md
pdfget-0.1.2.dist-info/RECORD
