Metadata-Version: 2.4
Name: pdfget
Version: 0.1.2
Summary: 智能文献搜索与批量下载工具，支持高级检索和并发下载
Author-email: gqy <qingyu_ge@foxmail.com>
License: MIT
License-File: LICENSE.md
Requires-Python: >=3.12
Requires-Dist: pandas>=2.0.0
Requires-Dist: requests>=2.31.0
